apparel_cli/__init__.py
apparel_cli/auth.py
apparel_cli/main.py
apparel_cli/problem.py
apparel_cli_scaffold-0.0.1.dist-info/METADATA
apparel_cli_scaffold-0.0.1.dist-info/WHEEL
apparel_cli_scaffold-0.0.1.dist-info/entry_points.txt
apparel_cli_scaffold-0.0.1.dist-info/top_level.txt
apparel_cli_scaffold-0.0.1.dist-info/RECORD
