Metadata-Version: 2.1
Name: apparel-cli-scaffold
Version: 0.0.1
Summary: Apparel CLI entry point
Home-page: https://github.com/apparel-cli-scaffold
Author: Bill de hÓra
Author-email: bill@dehora.net
License: MIT License
Platform: UNKNOWN
Classifier: Development Status :: 3 - Alpha
Classifier: Intended Audience :: Developers
Classifier: Natural Language :: English
Classifier: License :: OSI Approved :: MIT License
Classifier: Programming Language :: Python
Classifier: Programming Language :: Python :: 3.6
Requires-Python: ~=3.3
Requires-Dist: requests (>=2.18.0)
Requires-Dist: click (>=6.7)
Requires-Dist: clickclick (>=1.2.2)
Requires-Dist: click-plugins (>=1.0.3)
Requires-Dist: stups-zign (==1.1.31)
